independent_vector_analysis/__init__.py
independent_vector_analysis/consistent_iva.py
independent_vector_analysis/data_generation.py
independent_vector_analysis/helpers_iva.py
independent_vector_analysis/initializations.py
independent_vector_analysis/iva_g.py
independent_vector_analysis/iva_l_sos.py
independent_vector_analysis/visualization.py
independent_vector_analysis-0.3.4.dist-info/LICENSE
independent_vector_analysis-0.3.4.dist-info/METADATA
independent_vector_analysis-0.3.4.dist-info/WHEEL
independent_vector_analysis-0.3.4.dist-info/top_level.txt
independent_vector_analysis-0.3.4.dist-info/RECORD
