Metadata-Version: 2.1
Name: independent_vector_analysis
Version: 0.3.4
Summary: Implementation of IVA-G and IVA-L-SOS
Home-page: https://github.com/SSTGroup/independent_vector_analysis
Author: Isabell Lehmann
Author-email: isabell.lehmann@sst.upb.de
License: LICENSE
Keywords: iva,independent vector analysis,bss,multiset analysis
Classifier: Programming Language :: Python :: 3
Classifier: License :: OSI Approved :: MIT License
Classifier: Operating System :: OS Independent
Requires-Python: >=3.6
License-File: LICENSE
Requires-Dist: numpy
Requires-Dist: scipy
Requires-Dist: pytest
Requires-Dist: joblib
Requires-Dist: tqdm
Requires-Dist: matplotlib
